<?xml version="1.0" encoding="utf-8" ?><dwsync><file name="analytics.php" server="getyourticket.events" local="3811346197" remote="3795112800" Dst="-1" /><file name="bread.php" server="getyourticket.events" local="3811346197" remote="3795112800" Dst="-1" /><file name="compass.php" server="getyourticket.events" local="3811346198" remote="3795112800" Dst="-1" /><file name="database.php" server="getyourticket.events" local="3811346198" remote="3795112800" Dst="-1" /><file name="datatable.php" server="getyourticket.events" local="3811346198" remote="3795112800" Dst="-1" /><file name="date.php" server="getyourticket.events" local="3811346198" remote="3795112800" Dst="-1" /><file name="dimmer.php" server="getyourticket.events" local="3811346198" remote="3795112800" Dst="-1" /><file name="error.php" server="getyourticket.events" local="3811346198" remote="3795112800" Dst="-1" /><file name="form.php" server="getyourticket.events" local="3811346199" remote="3795112800" Dst="-1" /><file name="generic.php" server="getyourticket.events" local="3811346199" remote="3795112800" Dst="-1" /><file name="json.php" server="getyourticket.events" local="3811346199" remote="3795112800" Dst="-1" /><file name="login.php" server="getyourticket.events" local="3811346199" remote="3795112800" Dst="-1" /><file name="media.php" server="getyourticket.events" local="3811346199" remote="3795112800" Dst="-1" /><file name="menu_builder.php" server="getyourticket.events" local="3811346199" remote="3795112800" Dst="-1" /><file name="post.php" server="getyourticket.events" local="3811346199" remote="3795112800" Dst="-1" /><file name="profile.php" server="getyourticket.events" local="3811346199" remote="3795112800" Dst="-1" /><file name="seeders.php" server="getyourticket.events" local="3811346199" remote="3795112800" Dst="-1" /><file name="settings.php" server="getyourticket.events" local="3811346199" remote="3795112800" Dst="-1" /><file name="theme.php" server="getyourticket.events" local="3811346200" remote="3795112800" Dst="-1" /></dwsync>